{
  "root_text": {
    "uid": "sn22.44",
    "lang": "vi",
    "is_root": false,
    "title": "Con Ðường",
    "author": "Thích Minh Châu",
    "author_short": "Minh Châu",
    "author_uid": "minh_chau",
    "next": {
      "author_uid": "minh_chau",
      "lang": "vi",
      "name": "Impermanence ",
      "uid": "sn22.45"
    },
    "previous": {
      "author_uid": "minh_chau",
      "lang": "vi",
      "name": "Be Your Own Island ",
      "uid": "sn22.43"
    },
    "text": "<!DOCTYPE html>\n<html>\n<head>\n<meta charset='UTF-8'>\n<meta name='author' content='Thích Minh Châu'>\n<title></title>\n</head>\n<body>\n<article id='sn22.44' lang='vi'>\n<header>\n<ul>\n<li class='division'>Chương 22: Tương Ưng Uẩn</li>\n<li>V: Phẩm Tự Mình Làm Hòn Ðảo.</li>\n</ul>\n<h1>22.44. Con Ðường</h1>\n</header>\n<p><a class='pts' id='S.iii.44' href='#S.iii.44'></a><a class='vnO' id='Ðại.2,8a'></a><a class='ref vi-n' id='vi-n1-2.' href='#vi-n1-2.'>Vi-n 1-2.</a> Nhân duyên ở <i lang='pli' translate='no'>Sāvatthi</i> …</p>\n<p><a class='ref vi-n' id='vi-n3' href='#vi-n3'>Vi-n 3</a> —Này các Tỷ-kheo, Ta sẽ giảng cho các Ông con đường đưa đến thân kiến tập khởi và con đường đưa đến thân kiến đoạn diệt. Hãy lắng nghe.</p>\n<p><a class='ref vi-n' id='vi-n4' href='#vi-n4'>Vi-n 4</a> Và này các Tỷ-kheo, thế nào là con đường đưa đến thân kiến tập khởi?</p>\n<p><a class='ref vi-n' id='vi-n5' href='#vi-n5'>Vi-n 5</a> Ở đây, này các Tỷ-kheo, kẻ vô văn phàm phu không thấy rõ các bậc Thánh, không thuần thục pháp các bậc Thánh, không tu tập pháp các bậc Thánh, không thấy rõ các bậc Chân nhân, không thuần thục pháp các bậc Chân nhân, không tu tập pháp các bậc Chân nhân; quán sắc như là tự ngã, hay tự ngã như là có sắc, hay sắc ở trong tự ngã, hay tự ngã ở trong sắc.</p>\n<p><a class='ref vi-n' id='vi-n6-8.' href='#vi-n6-8.'>Vi-n 6-8.</a> … quán thọ … quán tưởng … quán các hành …</p>\n<p><a class='ref vi-n' id='vi-n9' href='#vi-n9'>Vi-n 9</a> … quán thức như là tự ngã, hay tự ngã như là có thức, hay thức ở trong tự ngã, hay tự ngã ở trong thức.</p>\n<p><a class='ref vi-n' id='vi-n10' href='#vi-n10'>Vi-n 10</a> Này các Tỷ-kheo, đây gọi là con đường đưa đến thân kiến tập khởi. Con đường đưa đến thân kiến tập khởi có nghĩa là: Sự quán sát đưa đến khổ tập khởi.</p>\n<p><a class='ref vi-n' id='vi-n11' href='#vi-n11'>Vi-n 11</a> Và này các Tỷ-kheo, thế nào là con đường đưa đến thân kiến đoạn diệt?</p>\n<p><a class='ref vi-n' id='vi-n12' href='#vi-n12'>Vi-n 12</a> Ở đây, này các Tỷ-kheo, vị Ða văn Thánh đệ tử thấy rõ các bậc Thánh, thuần thục pháp các bậc Thánh, tu tập pháp các bậc Thánh, thấy rõ các bậc Chân nhân, thuần thục pháp các bậc Chân nhân, tu tập pháp các bậc Chân nhân; không quán sắc như là tự ngã, hay không quán tự ngã như là có sắc, hay không quán sắc ở trong tự ngã, hay không quán tự ngã ở trong sắc.</p>\n<p><a class='ref vi-n' id='vi-n13-15.' href='#vi-n13-15.'>Vi-n 13-15.</a> … không quán thọ … không quán tưởng … không quán các hành …</p>\n<p><a class='ref vi-n' id='vi-n16' href='#vi-n16'>Vi-n 16</a> … không quán thức như là tự ngã, hay không quán tự ngã như là có thức, hay không quán thức ở trong tự ngã, hay không quán tự ngã ở trong thức.</p>\n<p><a class='ref vi-n' id='vi-n17' href='#vi-n17'>Vi-n 17</a> Này các Tỷ-kheo, đây gọi là con đường đưa đến thân kiến đoạn diệt. Con đường đưa đến thân kiến đoạn diệt có nghĩa là: Sự quán sát đưa đến sự khổ đoạn diệt.</p>\n<footer>\n<p>Bộ kinh đã được <span class='author'>Hòa thượng Thích Minh Châu</span> dịch sang Việt ngữ và Thiền viện Vạn Hạnh phát hành trong đầu thập niên <span class='publication-date'>1980</span>. Sau đó, trong chương trình phiên dịch và ấn hành Ðại tạng kinh Việt Nam, bộ kinh được tái bản năm 1993 và có số thứ tự từ 12 đến 16.</p>\n<p>Prepared for SuttaCentral by <span class='editor'>Blake Walsh</span>.</p>\n</footer>\n</article>\n</body>\n</html>\n"
  },
  "translation": {
    "uid": "sn22.44",
    "lang": "vi",
    "is_root": false,
    "title": "Con Ðường",
    "author": "Thích Minh Châu",
    "author_short": "Minh Châu",
    "author_uid": "minh_chau",
    "next": {
      "author_uid": "minh_chau",
      "lang": "vi",
      "name": "Impermanence ",
      "uid": "sn22.45"
    },
    "previous": {
      "author_uid": "minh_chau",
      "lang": "vi",
      "name": "Be Your Own Island ",
      "uid": "sn22.43"
    },
    "text": "<!DOCTYPE html>\n<html>\n<head>\n<meta charset='UTF-8'>\n<meta name='author' content='Thích Minh Châu'>\n<title></title>\n</head>\n<body>\n<article id='sn22.44' lang='vi'>\n<header>\n<ul>\n<li class='division'>Chương 22: Tương Ưng Uẩn</li>\n<li>V: Phẩm Tự Mình Làm Hòn Ðảo.</li>\n</ul>\n<h1>22.44. Con Ðường</h1>\n</header>\n<p><a class='pts' id='S.iii.44' href='#S.iii.44'></a><a class='vnO' id='Ðại.2,8a'></a><a class='ref vi-n' id='vi-n1-2.' href='#vi-n1-2.'>Vi-n 1-2.</a> Nhân duyên ở <i lang='pli' translate='no'>Sāvatthi</i> …</p>\n<p><a class='ref vi-n' id='vi-n3' href='#vi-n3'>Vi-n 3</a> —Này các Tỷ-kheo, Ta sẽ giảng cho các Ông con đường đưa đến thân kiến tập khởi và con đường đưa đến thân kiến đoạn diệt. Hãy lắng nghe.</p>\n<p><a class='ref vi-n' id='vi-n4' href='#vi-n4'>Vi-n 4</a> Và này các Tỷ-kheo, thế nào là con đường đưa đến thân kiến tập khởi?</p>\n<p><a class='ref vi-n' id='vi-n5' href='#vi-n5'>Vi-n 5</a> Ở đây, này các Tỷ-kheo, kẻ vô văn phàm phu không thấy rõ các bậc Thánh, không thuần thục pháp các bậc Thánh, không tu tập pháp các bậc Thánh, không thấy rõ các bậc Chân nhân, không thuần thục pháp các bậc Chân nhân, không tu tập pháp các bậc Chân nhân; quán sắc như là tự ngã, hay tự ngã như là có sắc, hay sắc ở trong tự ngã, hay tự ngã ở trong sắc.</p>\n<p><a class='ref vi-n' id='vi-n6-8.' href='#vi-n6-8.'>Vi-n 6-8.</a> … quán thọ … quán tưởng … quán các hành …</p>\n<p><a class='ref vi-n' id='vi-n9' href='#vi-n9'>Vi-n 9</a> … quán thức như là tự ngã, hay tự ngã như là có thức, hay thức ở trong tự ngã, hay tự ngã ở trong thức.</p>\n<p><a class='ref vi-n' id='vi-n10' href='#vi-n10'>Vi-n 10</a> Này các Tỷ-kheo, đây gọi là con đường đưa đến thân kiến tập khởi. Con đường đưa đến thân kiến tập khởi có nghĩa là: Sự quán sát đưa đến khổ tập khởi.</p>\n<p><a class='ref vi-n' id='vi-n11' href='#vi-n11'>Vi-n 11</a> Và này các Tỷ-kheo, thế nào là con đường đưa đến thân kiến đoạn diệt?</p>\n<p><a class='ref vi-n' id='vi-n12' href='#vi-n12'>Vi-n 12</a> Ở đây, này các Tỷ-kheo, vị Ða văn Thánh đệ tử thấy rõ các bậc Thánh, thuần thục pháp các bậc Thánh, tu tập pháp các bậc Thánh, thấy rõ các bậc Chân nhân, thuần thục pháp các bậc Chân nhân, tu tập pháp các bậc Chân nhân; không quán sắc như là tự ngã, hay không quán tự ngã như là có sắc, hay không quán sắc ở trong tự ngã, hay không quán tự ngã ở trong sắc.</p>\n<p><a class='ref vi-n' id='vi-n13-15.' href='#vi-n13-15.'>Vi-n 13-15.</a> … không quán thọ … không quán tưởng … không quán các hành …</p>\n<p><a class='ref vi-n' id='vi-n16' href='#vi-n16'>Vi-n 16</a> … không quán thức như là tự ngã, hay không quán tự ngã như là có thức, hay không quán thức ở trong tự ngã, hay không quán tự ngã ở trong thức.</p>\n<p><a class='ref vi-n' id='vi-n17' href='#vi-n17'>Vi-n 17</a> Này các Tỷ-kheo, đây gọi là con đường đưa đến thân kiến đoạn diệt. Con đường đưa đến thân kiến đoạn diệt có nghĩa là: Sự quán sát đưa đến sự khổ đoạn diệt.</p>\n<footer>\n<p>Bộ kinh đã được <span class='author'>Hòa thượng Thích Minh Châu</span> dịch sang Việt ngữ và Thiền viện Vạn Hạnh phát hành trong đầu thập niên <span class='publication-date'>1980</span>. Sau đó, trong chương trình phiên dịch và ấn hành Ðại tạng kinh Việt Nam, bộ kinh được tái bản năm 1993 và có số thứ tự từ 12 đến 16.</p>\n<p>Prepared for SuttaCentral by <span class='editor'>Blake Walsh</span>.</p>\n</footer>\n</article>\n</body>\n</html>\n"
  },
  "segmented": false,
  "suttaplex": {
    "acronym": "SN 22.44",
    "volpages": " PTS 3.44",
    "alt_volpages": null,
    "uid": "sn22.44",
    "blurb": "Contemplation of the five aggregates as not-self is the path to the end of identity.",
    "difficulty": null,
    "original_title": "Paṭipadāsutta",
    "root_lang": "pli",
    "root_lang_name": "Pāli",
    "type": "leaf",
    "from": null,
    "translated_title": "Con Ðường",
    "translations": [
      {
        "lang": "de",
        "lang_name": "Deutsch",
        "is_root": false,
        "author": "Sabbamitta",
        "author_short": "sabbamitta",
        "author_uid": "sabbamitta",
        "publication_date": "2019",
        "id": "sn22.44_translation-de-sabbamitta",
        "segmented": true,
        "title": "Übung ",
        "volpage": null,
        "has_comment": false
      },
      {
        "lang": "en",
        "lang_name": "English",
        "is_root": false,
        "author": "Bhikkhu Sujato",
        "author_short": "sujato",
        "author_uid": "sujato",
        "publication_date": "2018",
        "id": "sn22.44_translation-en-sujato",
        "segmented": true,
        "title": "Practice ",
        "volpage": null,
        "has_comment": true
      },
      {
        "lang": "pli",
        "lang_name": "Pāli",
        "is_root": true,
        "author": "Mahāsaṅgīti Tipiṭaka Buddhavasse 2500",
        "author_short": "ms",
        "author_uid": "ms",
        "publication_date": null,
        "id": "sn22.44_root-pli-ms",
        "segmented": true,
        "title": null,
        "volpage": null,
        "has_comment": false
      },
      {
        "lang": "bn",
        "lang_name": "বাংলা",
        "is_root": false,
        "author": "ইন্দ্রগুপ্ত ভিক্ষু, সুমন ভিক্ষু, আদিকল্যাণ ভিক্ষু, সীবক ভিক্ষু, রাহুল ভিক্ষু",
        "author_short": "ইন্দ্রগুপ্ত …",
        "author_uid": "indragupta-suman-adikalyan-sivak-rahul",
        "publication_date": "2018",
        "id": "bn_sn22.44_indragupta-suman-adikalyan-sivak-rahul",
        "segmented": false,
        "volpage": null,
        "has_comment": false
      },
      {
        "lang": "de",
        "lang_name": "Deutsch",
        "is_root": false,
        "author": "Nyanaponika Thera",
        "author_short": "Nyanaponika",
        "author_uid": "nyanaponika",
        "publication_date": "1967",
        "id": "de_sn22.44_nyanaponika",
        "segmented": false,
        "volpage": null,
        "has_comment": false
      },
      {
        "lang": "en",
        "lang_name": "English",
        "is_root": false,
        "author": "Bhikkhu Bodhi",
        "author_short": "Bodhi",
        "author_uid": "bodhi",
        "publication_date": "2000",
        "id": "en_sn22.44_bodhi",
        "segmented": false,
        "volpage": null,
        "has_comment": false
      },
      {
        "lang": "es",
        "lang_name": "Español",
        "is_root": false,
        "author": "Anton P. Baron",
        "author_short": "Baron",
        "author_uid": "baron",
        "publication_date": "2011",
        "id": "es_sn22.44_baron",
        "segmented": false,
        "volpage": null,
        "has_comment": false
      },
      {
        "lang": "hu",
        "lang_name": "Magyar",
        "is_root": false,
        "author": "Bartha Rita",
        "author_short": "Bartha",
        "author_uid": "bartha",
        "publication_date": "2009",
        "id": "hu_sn22.44_bartha",
        "segmented": false,
        "volpage": null,
        "has_comment": false
      },
      {
        "lang": "id",
        "lang_name": "Bahasa Indonesia",
        "is_root": false,
        "author": "Indra Anggara",
        "author_short": "Anggara",
        "author_uid": "anggara",
        "publication_date": null,
        "id": "id_sn22.44_anggara",
        "segmented": false,
        "volpage": null,
        "has_comment": false
      },
      {
        "lang": "jpn",
        "lang_name": "日本語",
        "is_root": false,
        "author": "関西パーリ語実習会",
        "author_short": "関西パーリ語実習会",
        "author_uid": "kansai",
        "publication_date": "2023",
        "id": "jpn_sn22.44_kansai",
        "segmented": false,
        "volpage": null,
        "has_comment": false
      },
      {
        "lang": "my",
        "lang_name": "မြန်မာဘာသာ",
        "is_root": false,
        "author": "Pitaka Myanmar Translation",
        "author_short": "PMT",
        "author_uid": "pmt",
        "publication_date": null,
        "id": "my_sn22.44_pmt",
        "segmented": false,
        "volpage": null,
        "has_comment": false
      },
      {
        "lang": "no",
        "lang_name": "Norsk",
        "is_root": false,
        "author": "Kåre A. Lie",
        "author_short": "Lie",
        "author_uid": "lie",
        "publication_date": "2017",
        "id": "no_sn22.44_lie",
        "segmented": false,
        "volpage": null,
        "has_comment": false
      },
      {
        "lang": "pt",
        "lang_name": "Português",
        "is_root": false,
        "author": "Michael Beisert",
        "author_short": "Beisert",
        "author_uid": "beisert",
        "publication_date": "2006",
        "id": "pt_sn22.44_beisert",
        "segmented": false,
        "volpage": null,
        "has_comment": false
      },
      {
        "lang": "ru",
        "lang_name": "Русский",
        "is_root": false,
        "author": "SV",
        "author_short": "SV",
        "author_uid": "sv",
        "publication_date": "2012",
        "id": "ru_sn22.44_sv",
        "segmented": false,
        "volpage": null,
        "has_comment": false
      },
      {
        "lang": "si",
        "lang_name": "සිංහල",
        "is_root": false,
        "author": "A.P. de Zoysa",
        "author_short": "Zoysa",
        "author_uid": "zoysa",
        "publication_date": null,
        "id": "si_sn22.44_zoysa",
        "segmented": false,
        "volpage": null,
        "has_comment": false
      },
      {
        "lang": "th",
        "lang_name": "ไทย",
        "is_root": false,
        "author": "Siam Rath",
        "author_short": "Siam Rath",
        "author_uid": "siam_rath",
        "publication_date": null,
        "id": "th_sn22.44_siam_rath",
        "segmented": false,
        "volpage": null,
        "has_comment": false
      },
      {
        "author": "Thích Minh Châu",
        "author_short": "Minh Châu",
        "author_uid": "minh_chau",
        "has_comment": false,
        "id": "vi_sn22.44_minh_chau",
        "is_root": false,
        "lang": "vi",
        "lang_name": "Tiếng Việt",
        "publication_date": "1980",
        "segmented": false,
        "volpage": null,
        "title": "Con Ðường"
      },
      {
        "lang": "zh",
        "lang_name": "汉语",
        "is_root": false,
        "author": "莊春江",
        "author_short": "莊春江",
        "author_uid": "zhuang",
        "publication_date": null,
        "id": "zh_sn22.44_zhuang",
        "segmented": false,
        "volpage": null,
        "has_comment": false
      }
    ],
    "parallel_count": 11,
    "biblio": null,
    "priority_author_uid": null,
    "verseNo": "bj15.80, dr17.54, ms13S3_196, msdiv44, pts-vp-pli3.44,cck17.40, csp1ed13.37, csp2ed13.37, dr17.55, ms13S3_197, sya17.56",
    "previous": {
      "name": null,
      "uid": null
    },
    "next": {
      "name": null,
      "uid": null
    }
  },
  "bilara_root_text": {
    "uid": "sn22.44",
    "author": "Mahāsaṅgīti Tipiṭaka Buddhavasse 2500",
    "author_short": "ms",
    "author_uid": "ms",
    "lang": "pli",
    "title": "Paṭipadāsutta",
    "previous": {
      "author_uid": "ms",
      "lang": "pli",
      "name": null,
      "uid": null
    },
    "next": {
      "author_uid": "ms",
      "lang": "pli",
      "name": null,
      "uid": null
    }
  },
  "bilara_translated_text": null,
  "candidate_authors": [
    "sujato",
    "bodhi"
  ]
}