{
  "root_text": {
    "uid": "kp1",
    "lang": "vi",
    "is_root": false,
    "title": "Tam Quy",
    "author": "Thích Minh Châu",
    "author_short": "Minh Châu",
    "author_uid": "minh_chau",
    "next": {
      "author_uid": "minh_chau",
      "lang": "vi",
      "name": "The Ten Precepts ",
      "uid": "kp2"
    },
    "previous": null,
    "text": "<!DOCTYPE html>\n<html>\n<head>\n<meta charset='UTF-8'>\n<meta name='author' content='Thích Minh Châu'>\n<title></title>\n</head>\n<body>\n<article id='kp1' lang='vi'>\n<header>\n<ul>\n<li class='division'>TIỂU BỘ KINH</li>\n<li class='subdivision'>TIỂU TỤNG</li>\n</ul>\n<h1>1. Tam Quy</h1>\n</header>\n<p>Ðệ tử quy y Phật,</p>\n<p>Ðệ tử quy y Pháp,</p>\n<p>Ðệ tử quy y Tăng.</p>\n<p>Lần thứ hai đệ tử quy y Phật,</p>\n<p>Lần thứ hai đệ tử quy y Pháp,</p>\n<p>Lần thứ hai đệ tử quy y Tăng.</p>\n<p>Lần thứ ba đệ tử quy y Phật</p>\n<p>Lần thứ ba đệ tử quy y Pháp.</p>\n<p>Lần thứ ba đệ tử quy y Tăng.</p>\n<footer>\n<p>Translated by <span class='author'>Thích Minh Châu</span>.</p>\n<p>Prepared for SuttaCentral by <span class='editor'>Ven. Vimala</span>.</p>\n</footer>\n</article>\n</body>\n</html>\n"
  },
  "translation": {
    "uid": "kp1",
    "lang": "vi",
    "is_root": false,
    "title": "Tam Quy",
    "author": "Thích Minh Châu",
    "author_short": "Minh Châu",
    "author_uid": "minh_chau",
    "next": {
      "author_uid": "minh_chau",
      "lang": "vi",
      "name": "The Ten Precepts ",
      "uid": "kp2"
    },
    "previous": null,
    "text": "<!DOCTYPE html>\n<html>\n<head>\n<meta charset='UTF-8'>\n<meta name='author' content='Thích Minh Châu'>\n<title></title>\n</head>\n<body>\n<article id='kp1' lang='vi'>\n<header>\n<ul>\n<li class='division'>TIỂU BỘ KINH</li>\n<li class='subdivision'>TIỂU TỤNG</li>\n</ul>\n<h1>1. Tam Quy</h1>\n</header>\n<p>Ðệ tử quy y Phật,</p>\n<p>Ðệ tử quy y Pháp,</p>\n<p>Ðệ tử quy y Tăng.</p>\n<p>Lần thứ hai đệ tử quy y Phật,</p>\n<p>Lần thứ hai đệ tử quy y Pháp,</p>\n<p>Lần thứ hai đệ tử quy y Tăng.</p>\n<p>Lần thứ ba đệ tử quy y Phật</p>\n<p>Lần thứ ba đệ tử quy y Pháp.</p>\n<p>Lần thứ ba đệ tử quy y Tăng.</p>\n<footer>\n<p>Translated by <span class='author'>Thích Minh Châu</span>.</p>\n<p>Prepared for SuttaCentral by <span class='editor'>Ven. Vimala</span>.</p>\n</footer>\n</article>\n</body>\n</html>\n"
  },
  "segmented": false,
  "suttaplex": {
    "acronym": "Kp 1",
    "volpages": " PTS 1",
    "alt_volpages": null,
    "uid": "kp1",
    "blurb": "The three refuges formula",
    "difficulty": null,
    "original_title": "Saraṇattaya",
    "root_lang": "pli",
    "root_lang_name": "Pāli",
    "type": "leaf",
    "from": null,
    "translated_title": "Tam Quy",
    "translations": [
      {
        "lang": "de",
        "lang_name": "Deutsch",
        "is_root": false,
        "author": "Sabbamitta",
        "author_short": "sabbamitta",
        "author_uid": "sabbamitta",
        "publication_date": "2021",
        "id": "kp1_translation-de-sabbamitta",
        "segmented": true,
        "title": "Die dreifache Zuflucht ",
        "volpage": null,
        "has_comment": false
      },
      {
        "lang": "en",
        "lang_name": "English",
        "is_root": false,
        "author": "Bhikkhu Sujato",
        "author_short": "sujato",
        "author_uid": "sujato",
        "publication_date": "2020",
        "id": "kp1_translation-en-sujato",
        "segmented": true,
        "title": "The Three Refuges ",
        "volpage": null,
        "has_comment": false
      },
      {
        "lang": "pl",
        "lang_name": "Polski",
        "is_root": false,
        "author": "Piotr Jagodziński",
        "author_short": "hardao",
        "author_uid": "hardao",
        "publication_date": "2023",
        "id": "kp1_translation-pl-hardao",
        "segmented": true,
        "title": "Trzy Schronienia ",
        "volpage": null,
        "has_comment": false
      },
      {
        "lang": "pli",
        "lang_name": "Pāli",
        "is_root": true,
        "author": "Mahāsaṅgīti Tipiṭaka Buddhavasse 2500",
        "author_short": "ms",
        "author_uid": "ms",
        "publication_date": null,
        "id": "kp1_root-pli-ms",
        "segmented": true,
        "title": null,
        "volpage": null,
        "has_comment": false
      },
      {
        "lang": "pt",
        "lang_name": "Português",
        "is_root": false,
        "author": "Laera et al.",
        "author_short": "laera",
        "author_uid": "laera",
        "publication_date": null,
        "id": "kp1_translation-pt-laera-quaresma",
        "segmented": true,
        "title": "Os Três Refúgios ",
        "volpage": null,
        "has_comment": false
      },
      {
        "lang": "de",
        "lang_name": "Deutsch",
        "is_root": false,
        "author": "Karl Seidenstücker",
        "author_short": "Seidenstücker",
        "author_uid": "seidenstuecker",
        "publication_date": "1910",
        "id": "de_kp1_seidenstuecker",
        "segmented": false,
        "volpage": null,
        "has_comment": false
      },
      {
        "lang": "en",
        "lang_name": "English",
        "is_root": false,
        "author": "Bhikkhu Ānandajoti",
        "author_short": "Ānandajoti",
        "author_uid": "anandajoti",
        "publication_date": null,
        "id": "en_kp1_anandajoti",
        "segmented": false,
        "volpage": null,
        "has_comment": false
      },
      {
        "lang": "en",
        "lang_name": "English",
        "is_root": false,
        "author": "Piyadassi Thera",
        "author_short": "Piyadassi",
        "author_uid": "piyadassi",
        "publication_date": "1999",
        "id": "en_kp1_piyadassi",
        "segmented": false,
        "volpage": null,
        "has_comment": false
      },
      {
        "lang": "it",
        "lang_name": "Italiano",
        "is_root": false,
        "author": "Enzo Alfano",
        "author_short": "Alfano",
        "author_uid": "alfano",
        "publication_date": null,
        "id": "it_kp1_alfano",
        "segmented": false,
        "volpage": null,
        "has_comment": false
      },
      {
        "lang": "jpn",
        "lang_name": "日本語",
        "is_root": false,
        "author": "関西パーリ語実習会",
        "author_short": "関西パーリ語実習会",
        "author_uid": "kansai",
        "publication_date": "2023",
        "id": "jpn_kp1_kansai",
        "segmented": false,
        "volpage": null,
        "has_comment": false
      },
      {
        "lang": "my",
        "lang_name": "မြန်မာဘာသာ",
        "is_root": false,
        "author": "Pitaka Myanmar Translation",
        "author_short": "PMT",
        "author_uid": "pmt",
        "publication_date": null,
        "id": "my_kp1_pmt",
        "segmented": false,
        "volpage": null,
        "has_comment": false
      },
      {
        "lang": "nl",
        "lang_name": "Nederlands",
        "is_root": false,
        "author": "Guy Eugène Dubois",
        "author_short": "Dubois",
        "author_uid": "dubois",
        "publication_date": null,
        "id": "nl_kp1_dubois",
        "segmented": false,
        "volpage": null,
        "has_comment": false
      },
      {
        "lang": "si",
        "lang_name": "සිංහල",
        "is_root": false,
        "author": "A.P. de Zoysa",
        "author_short": "Zoysa",
        "author_uid": "zoysa",
        "publication_date": null,
        "id": "si_kp1_zoysa",
        "segmented": false,
        "volpage": null,
        "has_comment": false
      },
      {
        "lang": "ta",
        "lang_name": "தமிழ்",
        "is_root": false,
        "author": "Ben Arasu",
        "author_short": "Arasu",
        "author_uid": "arasu",
        "publication_date": null,
        "id": "ta_kp1_arasu",
        "segmented": false,
        "volpage": null,
        "has_comment": false
      },
      {
        "author": "Thích Minh Châu",
        "author_short": "Minh Châu",
        "author_uid": "minh_chau",
        "has_comment": false,
        "id": "vi_kp1_minh_chau",
        "is_root": false,
        "lang": "vi",
        "lang_name": "Tiếng Việt",
        "publication_date": null,
        "segmented": false,
        "volpage": null,
        "title": "Tam Quy"
      },
      {
        "lang": "zh",
        "lang_name": "汉语",
        "is_root": false,
        "author": "Metta",
        "author_short": "Metta",
        "author_uid": "metta",
        "publication_date": null,
        "id": "zh_kp1_metta",
        "segmented": false,
        "volpage": null,
        "has_comment": false
      }
    ],
    "parallel_count": 1,
    "biblio": null,
    "priority_author_uid": null,
    "verseNo": "ms18Kh_1,bj24.2, cck25.1, csp1ed18.1, csp2ed18.1, dr25.1, mc0.1, ms18Kh_2, msdiv1, ndp20.3, pts-vp-pli1, sya25.1, vri47.1,ms18Kh_3,ms18Kh_4, vri47.2,ms18Kh_5",
    "previous": {
      "name": null,
      "uid": null
    },
    "next": {
      "name": null,
      "uid": null
    }
  },
  "bilara_root_text": {
    "uid": "kp1",
    "author": "Mahāsaṅgīti Tipiṭaka Buddhavasse 2500",
    "author_short": "ms",
    "author_uid": "ms",
    "lang": "pli",
    "title": "Saraṇattaya",
    "previous": {
      "author_uid": "ms",
      "lang": "pli",
      "name": null,
      "uid": null
    },
    "next": {
      "author_uid": "ms",
      "lang": "pli",
      "name": null,
      "uid": null
    }
  },
  "bilara_translated_text": null,
  "candidate_authors": [
    "sujato",
    "anandajoti",
    "piyadassi"
  ]
}